{"knowledges": [{"speaker": "Monica", "tokens": [{"index": 1, "word": "Well", "originalText": "Well", "lemma": "well", "characterOffsetBegin": 0, "characterOffsetEnd": 4, "pos": "RB", "before": "", "after": ""}, {"index": 2, "word": ",", "originalText": ",", "lemma": ",", "characterOffsetBegin": 4, "characterOffsetEnd": 5, "pos": ",", "before": "", "after": " "}, {"index": 3, "word": "I", "originalText": "I", "lemma": "I", "characterOffsetBegin": 6, "characterOffsetEnd": 7, "pos": "PRP", "before": " ", "after": ""}, {"index": 4, "word": "'m", "originalText": "'m", "lemma": "be", "characterOffsetBegin": 7, "characterOffsetEnd": 9, "pos": "VBP", "before": "", "after": " "}, {"index": 5, "word": "going", "originalText": "going", "lemma": "go", "characterOffsetBegin": 10, "characterOffsetEnd": 15, "pos": "VBG", "before": " ", "after": " "}, {"index": 6, "word": "out", "originalText": "out", "lemma": "out", "characterOffsetBegin": 16, "characterOffsetEnd": 19, "pos": "RP", "before": " ", "after": " "}, {"index": 7, "word": "with", "originalText": "with", "lemma": "with", "characterOffsetBegin": 20, "characterOffsetEnd": 24, "pos": "IN", "before": " ", "after": " "}, {"index": 8, "word": "a", "originalText": "a", "lemma": "a", "characterOffsetBegin": 25, "characterOffsetEnd": 26, "pos": "DT", "before": " ", "after": " "}, {"index": 9, "word": "guy", "originalText": "guy", "lemma": "guy", "characterOffsetBegin": 27, "characterOffsetEnd": 30, "pos": "NN", "before": " ", "after": " "}, {"index": 10, "word": "my", "originalText": "my", "lemma": "my", "characterOffsetBegin": 31, "characterOffsetEnd": 33, "pos": "PRP$", "before": " ", "after": " "}, {"index": 11, "word": "friends", "originalText": "friends", "lemma": "friend", "characterOffsetBegin": 34, "characterOffsetEnd": 41, "pos": "NNS", "before": " ", "after": " "}, {"index": 12, "word": "all", "originalText": "all", "lemma": "all", "characterOffsetBegin": 42, "characterOffsetEnd": 45, "pos": "DT", "before": " ", "after": " "}, {"index": 13, "word": "really", "originalText": "really", "lemma": "really", "characterOffsetBegin": 46, "characterOffsetEnd": 52, "pos": "RB", "before": " ", "after": " "}, {"index": 14, "word": "like", "originalText": "like", "lemma": "like", "characterOffsetBegin": 53, "characterOffsetEnd": 57, "pos": "IN", "before": " ", "after": ""}, {"index": 15, "word": ".", "originalText": ".", "lemma": ".", "characterOffsetBegin": 57, "characterOffsetEnd": 58, "pos": ".", "before": "", "after": ""}], "ext_links": {"frame": ["go", "Being_named", "Compatibility", "Motion", "Transition_to_a_quality", "Undergo_change"], "synsets": [{"lemma": "go", "synset": "Synset('travel.v.01')", "definition": "change location; move, travel, or proceed, also metaphorically", "lemma_names": ["travel", "go", "move", "locomote"], "_examples": ["How fast does your new car go?", "We travelled from Rome to Naples by bus", "The policemen went from door to door looking for the suspect", "The soldiers moved towards the city in an attempt to take it before night fell", "news travelled fast"]}, {"lemma": "go", "synset": "Synset('go.v.02')", "definition": "follow a procedure or take a course", "lemma_names": ["go", "proceed", "move"], "_examples": ["We should go farther in this matter", "She went through a lot of trouble", "go about the world in a certain manner", "Messages must go through diplomatic channels"]}, {"lemma": "go", "synset": "Synset('go.v.03')", "definition": "move away from a place into another direction", "lemma_names": ["go", "go_away", "depart"], "_examples": ["Go away before I start to cry", "The train departs at noon"]}, {"lemma": "go", "synset": "Synset('become.v.01')", "definition": "enter or assume a certain state or condition", "lemma_names": ["become", "go", "get"], "_examples": ["He became annoyed when he heard the bad news", "It must be getting more serious", "her face went red with anger", "She went into ecstasy", "Get going!"]}, {"lemma": "go", "synset": "Synset('go.v.05')", "definition": "be awarded; be allotted", "lemma_names": ["go"], "_examples": ["The first prize goes to Mary", "Her money went on clothes"]}, {"lemma": "go", "synset": "Synset('run.v.05')", "definition": "have a particular form", "lemma_names": ["run", "go"], "_examples": ["the story or argument runs as follows", "as the saying goes..."]}, {"lemma": "go", "synset": "Synset('run.v.03')", "definition": "stretch out over a distance, space, time, or scope; run or extend between two points or beyond a certain point", "lemma_names": ["run", "go", "pass", "lead", "extend"], "_examples": ["Service runs all the way to Cranbury", "His knowledge doesn't go very far", "My memory extends back to my fourth year of life", "The facts extend beyond a consideration of her personal assets"]}, {"lemma": "go", "synset": "Synset('proceed.v.04')", "definition": "follow a certain course", "lemma_names": ["proceed", "go"], "_examples": ["The inauguration went well", "how did your interview go?"]}, {"lemma": "go", "synset": "Synset('go.v.09')", "definition": "be abolished or discarded", "lemma_names": ["go"], "_examples": ["These ugly billboards have to go!", "These luxuries all had to go under the Khmer Rouge"]}, {"lemma": "go", "synset": "Synset('go.v.10')", "definition": "be or continue to be in a certain condition", "lemma_names": ["go"], "_examples": ["The children went hungry that day"]}, {"lemma": "go", "synset": "Synset('sound.v.02')", "definition": "make a certain noise or sound", "lemma_names": ["sound", "go"], "_examples": ["She went `Mmmmm'", "The gun went `bang'"]}, {"lemma": "go", "synset": "Synset('function.v.01')", "definition": "perform as expected when applied", "lemma_names": ["function", "work", "operate", "go", "run"], "_examples": ["The washing machine won't go unless it's plugged in", "Does this old car still run well?", "This old radio doesn't work anymore"]}, {"lemma": "go", "synset": "Synset('run_low.v.01')", "definition": "to be spent or finished", "lemma_names": ["run_low", "run_short", "go"], "_examples": ["The money had gone after a few days", "Gas is running low at the gas stations in the Midwest"]}, {"lemma": "go", "synset": "Synset('move.v.13')", "definition": "progress by being changed", "lemma_names": ["move", "go", "run"], "_examples": ["The speech has to go through several more drafts", "run through your presentation before the meeting"]}, {"lemma": "go", "synset": "Synset('survive.v.01')", "definition": "continue to live through hardship or adversity", "lemma_names": ["survive", "last", "live", "live_on", "go", "endure", "hold_up", "hold_out"], "_examples": ["We went without water and food for 3 days", "These superstitions survive in the backwaters of America", "The race car driver lived through several very serious accidents", "how long can a person last without food and water?"]}, {"lemma": "go", "synset": "Synset('go.v.16')", "definition": "pass, fare, or elapse; of a certain state of affairs or action", "lemma_names": ["go"], "_examples": ["How is it going?", "The day went well until I got your call"]}, {"lemma": "go", "synset": "Synset('die.v.01')", "definition": "pass from physical life and lose all bodily attributes and functions necessary to sustain life", "lemma_names": ["die", "decease", "perish", "go", "exit", "pass_away", "expire", "pass", "kick_the_bucket", "cash_in_one's_chips", "buy_the_farm", "conk", "give-up_the_ghost", "drop_dead", "pop_off", "choke", "croak", "snuff_it"], "_examples": ["She died from cancer", "The children perished in the fire", "The patient went peacefully", "The old guy kicked the bucket at the age of 102"]}, {"lemma": "go", "synset": "Synset('belong.v.03')", "definition": "be in the right place or situation", "lemma_names": ["belong", "go"], "_examples": ["Where do these books belong?", "Let's put health care where it belongs--under the control of the government", "Where do these books go?"]}, {"lemma": "go", "synset": "Synset('go.v.19')", "definition": "be ranked or compare", "lemma_names": ["go"], "_examples": ["This violinist is as good as Juilliard-trained violinists go"]}, {"lemma": "go", "synset": "Synset('start.v.09')", "definition": "begin or set in motion", "lemma_names": ["start", "go", "get_going"], "_examples": ["I start at eight in the morning", "Ready, set, go!"]}, {"lemma": "go", "synset": "Synset('move.v.15')", "definition": "have a turn; make one's move in a game", "lemma_names": ["move", "go"], "_examples": ["Can I go now?"]}, {"lemma": "go", "synset": "Synset('go.v.22')", "definition": "be contained in", "lemma_names": ["go"], "_examples": ["How many times does 18 go into 54?"]}, {"lemma": "go", "synset": "Synset('go.v.23')", "definition": "be sounded, played, or expressed", "lemma_names": ["go"], "_examples": ["How does this song go again?"]}, {"lemma": "go", "synset": "Synset('blend.v.02')", "definition": "blend or harmonize", "lemma_names": ["blend", "go", "blend_in"], "_examples": ["This flavor will blend with those in your dish", "This sofa won't go with the chairs"]}, {"lemma": "go", "synset": "Synset('go.v.25')", "definition": "lead, extend, or afford access", "lemma_names": ["go", "lead"], "_examples": ["This door goes to the basement", "The road runs South"]}, {"lemma": "go", "synset": "Synset('fit.v.02')", "definition": "be the right size or shape; fit correctly or as desired", "lemma_names": ["fit", "go"], "_examples": ["This piece won't fit into the puzzle"]}, {"lemma": "go", "synset": "Synset('rifle.v.02')", "definition": "go through in search of something; search through someone's belongings in an unauthorized way", "lemma_names": ["rifle", "go"], "_examples": ["Who rifled through my desk drawers?"]}, {"lemma": "go", "synset": "Synset('go.v.28')", "definition": "be spent", "lemma_names": ["go"], "_examples": ["All my money went for food and rent"]}, {"lemma": "go", "synset": "Synset('plump.v.04')", "definition": "give support (to) or make a choice (of) one out of a group or number", "lemma_names": ["plump", "go"], "_examples": ["I plumped for the losing candidates"]}, {"lemma": "go", "synset": "Synset('fail.v.04')", "definition": "stop operating or functioning", "lemma_names": ["fail", "go_bad", "give_way", "die", "give_out", "conk_out", "go", "break", "break_down"], "_examples": ["The engine finally went", "The car died on the road", "The bus we travelled in broke down on the way to town", "The coffee maker broke", "The engine failed on the way to town", "her eyesight went after the accident"]}]}, "characters": ["", "", "Monica", "", "", "", "", "", "", "Monica", "", "", "", "", ""], "sid": "0-1", "origin_sent": "Well, I'm going out with a guy my friends all really like.", "triple": {"sbj": "Monica", "rel": "be go out with", "obj": "guy"}, "intention": ["Well", "a", "my", "friends", "all", "really", "like"]}, {"speaker": "Paula", "tokens": [{"index": 1, "word": "you", "originalText": "you", "lemma": "you", "characterOffsetBegin": 0, "characterOffsetEnd": 3, "pos": "PRP", "before": "", "after": " "}, {"index": 2, "word": "should", "originalText": "should", "lemma": "should", "characterOffsetBegin": 4, "characterOffsetEnd": 10, "pos": "MD", "before": " ", "after": " "}, {"index": 3, "word": "always", "originalText": "always", "lemma": "always", "characterOffsetBegin": 11, "characterOffsetEnd": 17, "pos": "RB", "before": " ", "after": " "}, {"index": 4, "word": "feel", "originalText": "feel", "lemma": "feel", "characterOffsetBegin": 18, "characterOffsetEnd": 22, "pos": "VB", "before": " ", "after": " "}, {"index": 5, "word": "the", "originalText": "the", "lemma": "the", "characterOffsetBegin": 23, "characterOffsetEnd": 26, "pos": "DT", "before": " ", "after": " "}, {"index": 6, "word": "thing", "originalText": "thing", "lemma": "thing", "characterOffsetBegin": 27, "characterOffsetEnd": 32, "pos": "NN", "before": " ", "after": ""}, {"index": 7, "word": ".", "originalText": ".", "lemma": ".", "characterOffsetBegin": 32, "characterOffsetEnd": 33, "pos": ".", "before": "", "after": ""}], "ext_links": {"frame": ["feel", "Feeling", "Give_impression", "Opinion", "Perception_active", "Perception_experience", "Seeking"], "synsets": [{"lemma": "feel", "synset": "Synset('feel.v.01')", "definition": "undergo an emotional sensation or be in a particular state of mind", "lemma_names": ["feel", "experience"], "_examples": ["She felt resentful", "He felt regret"]}, {"lemma": "feel", "synset": "Synset('find.v.05')", "definition": "come to believe on the basis of emotion, intuitions, or indefinite grounds", "lemma_names": ["find", "feel"], "_examples": ["I feel that he doesn't like me", "I find him to be obnoxious", "I found the movie rather entertaining"]}, {"lemma": "feel", "synset": "Synset('feel.v.03')", "definition": "perceive by a physical sensation, e.g., coming from the skin or muscles", "lemma_names": ["feel", "sense"], "_examples": ["He felt the wind", "She felt an object brushing her arm", "He felt his flesh crawl", "She felt the heat when she got out of the car"]}, {"lemma": "feel", "synset": "Synset('feel.v.04')", "definition": "be conscious of a physical, mental, or emotional state", "lemma_names": ["feel"], "_examples": ["My cold is gone--I feel fine today", "She felt tired after the long hike", "She felt sad after her loss"]}, {"lemma": "feel", "synset": "Synset('feel.v.05')", "definition": "have a feeling or perception about oneself in reaction to someone's behavior or attitude", "lemma_names": ["feel"], "_examples": ["She felt small and insignificant", "You make me feel naked", "I made the students feel different about themselves"]}, {"lemma": "feel", "synset": "Synset('feel.v.06')", "definition": "undergo passive experience of:\"We felt the effects of inflation\"", "lemma_names": ["feel"], "_examples": ["her fingers felt their way through the string quartet", "she felt his contempt of her"]}, {"lemma": "feel", "synset": "Synset('feel.v.07')", "definition": "be felt or perceived in a certain way", "lemma_names": ["feel"], "_examples": ["The ground feels shaky", "The sheets feel soft"]}, {"lemma": "feel", "synset": "Synset('feel.v.08')", "definition": "grope or feel in search of something", "lemma_names": ["feel"], "_examples": ["He felt for his wallet"]}, {"lemma": "feel", "synset": "Synset('feel.v.09')", "definition": "examine by touch", "lemma_names": ["feel", "finger"], "_examples": ["Feel this soft cloth!", "The customer fingered the sweater"]}, {"lemma": "feel", "synset": "Synset('palpate.v.01')", "definition": "examine (a body part) by palpation", "lemma_names": ["palpate", "feel"], "_examples": ["The nurse palpated the patient's stomach", "The runner felt her pulse"]}, {"lemma": "feel", "synset": "Synset('feel.v.11')", "definition": "find by testing or cautious exploration", "lemma_names": ["feel"], "_examples": ["He felt his way around the dark room"]}, {"lemma": "feel", "synset": "Synset('feel.v.12')", "definition": "produce a certain impression", "lemma_names": ["feel"], "_examples": ["It feels nice to be home again"]}, {"lemma": "feel", "synset": "Synset('feel.v.13')", "definition": "pass one's hands over the sexual organs of", "lemma_names": ["feel"], "_examples": ["He felt the girl in the movie theater"]}]}, "characters": ["Monica", "", "", "", "", "", ""], "sid": "3-0", "origin_sent": "you should always feel the thing.", "triple": {"sbj": "Monica", "rel": "feel", "obj": "thing"}, "intention": ["should", "always", "the"]}, {"speaker": "Monica", "tokens": [{"index": 1, "word": "It", "originalText": "It", "lemma": "it", "characterOffsetBegin": 0, "characterOffsetEnd": 2, "pos": "PRP", "before": "", "after": ""}, {"index": 2, "word": "'s", "originalText": "'s", "lemma": "be", "characterOffsetBegin": 2, "characterOffsetEnd": 4, "pos": "VBZ", "before": "", "after": " "}, {"index": 3, "word": "the", "originalText": "the", "lemma": "the", "characterOffsetBegin": 5, "characterOffsetEnd": 8, "pos": "DT", "before": " ", "after": " "}, {"index": 4, "word": "other", "originalText": "other", "lemma": "other", "characterOffsetBegin": 9, "characterOffsetEnd": 14, "pos": "JJ", "before": " ", "after": " "}, {"index": 5, "word": "five", "originalText": "five", "lemma": "five", "characterOffsetBegin": 15, "characterOffsetEnd": 19, "pos": "CD", "before": " ", "after": " "}, {"index": 6, "word": "I", "originalText": "I", "lemma": "I", "characterOffsetBegin": 20, "characterOffsetEnd": 21, "pos": "PRP", "before": " ", "after": ""}, {"index": 7, "word": "'m", "originalText": "'m", "lemma": "be", "characterOffsetBegin": 21, "characterOffsetEnd": 23, "pos": "VBP", "before": "", "after": " "}, {"index": 8, "word": "worried", "originalText": "worried", "lemma": "worried", "characterOffsetBegin": 24, "characterOffsetEnd": 31, "pos": "JJ", "before": " ", "after": " "}, {"index": 9, "word": "about", "originalText": "about", "lemma": "about", "characterOffsetBegin": 32, "characterOffsetEnd": 37, "pos": "IN", "before": " ", "after": ""}, {"index": 10, "word": ".", "originalText": ".", "lemma": ".", "characterOffsetBegin": 37, "characterOffsetEnd": 38, "pos": ".", "before": "", "after": ""}], "ext_links": {"frame": ["be", "Performers_and_roles"], "synsets": [{"lemma": "be", "synset": "Synset('be.v.01')", "definition": "have the quality of being; (copula, used with an adjective or a predicate noun)", "lemma_names": ["be"], "_examples": ["John is rich", "This is not a good answer"]}, {"lemma": "be", "synset": "Synset('be.v.02')", "definition": "be identical to; be someone or something", "lemma_names": ["be"], "_examples": ["The president of the company is John Smith", "This is my house"]}, {"lemma": "be", "synset": "Synset('be.v.03')", "definition": "occupy a certain position or area; be somewhere", "lemma_names": ["be"], "_examples": ["Where is my umbrella?\" \"The toolshed is in the back", "What is behind this behavior?"]}, {"lemma": "be", "synset": "Synset('exist.v.01')", "definition": "have an existence, be extant", "lemma_names": ["exist", "be"], "_examples": ["Is there a God?"]}, {"lemma": "be", "synset": "Synset('be.v.05')", "definition": "happen, occur, take place; this was during the visit to my parents' house\"", "lemma_names": ["be"], "_examples": ["I lost my wallet", "There were two hundred people at his funeral", "There was a lot of noise in the kitchen"]}, {"lemma": "be", "synset": "Synset('equal.v.01')", "definition": "be identical or equivalent to", "lemma_names": ["equal", "be"], "_examples": ["One dollar equals 1,000 rubles these days!"]}, {"lemma": "be", "synset": "Synset('constitute.v.01')", "definition": "form or compose", "lemma_names": ["constitute", "represent", "make_up", "comprise", "be"], "_examples": ["This money is my only income", "The stone wall was the backdrop for the performance", "These constitute my entire belonging", "The children made up the chorus", "This sum represents my entire income for a year", "These few men comprise his entire army"]}, {"lemma": "be", "synset": "Synset('be.v.08')", "definition": "work in a specific place, with a specific subject, or in a specific function", "lemma_names": ["be", "follow"], "_examples": ["He is a herpetologist", "She is our resident philosopher"]}, {"lemma": "be", "synset": "Synset('embody.v.02')", "definition": "represent, as of a character on stage", "lemma_names": ["embody", "be", "personify"], "_examples": ["Derek Jacobi was Hamlet"]}, {"lemma": "be", "synset": "Synset('be.v.10')", "definition": "spend or use time", "lemma_names": ["be"], "_examples": ["I may be an hour"]}, {"lemma": "be", "synset": "Synset('be.v.11')", "definition": "have life, be alive", "lemma_names": ["be", "live"], "_examples": ["Our great leader is no more", "My grandfather lived until the end of war"]}, {"lemma": "be", "synset": "Synset('be.v.12')", "definition": "to remain unmolested, undisturbed, or uninterrupted -- used only in infinitive form", "lemma_names": ["be"], "_examples": ["let her be"]}, {"lemma": "be", "synset": "Synset('cost.v.01')", "definition": "be priced at", "lemma_names": ["cost", "be"], "_examples": ["These shoes cost $100"]}]}, "characters": ["", "", "", "", "", "Monica", "", "", "", ""], "sid": "6-1", "origin_sent": "It's the other five I'm worried about.", "triple": {"sbj": "Monica", "rel": "be", "obj": "worried about"}, "intention": ["It", "'s", "the", "other", "five"]}, {"speaker": "Monica", "tokens": [{"index": 1, "word": "It", "originalText": "It", "lemma": "it", "characterOffsetBegin": 0, "characterOffsetEnd": 2, "pos": "PRP", "before": "", "after": ""}, {"index": 2, "word": "'s", "originalText": "'s", "lemma": "be", "characterOffsetBegin": 2, "characterOffsetEnd": 4, "pos": "VBZ", "before": "", "after": " "}, {"index": 3, "word": "the", "originalText": "the", "lemma": "the", "characterOffsetBegin": 5, "characterOffsetEnd": 8, "pos": "DT", "before": " ", "after": " "}, {"index": 4, "word": "other", "originalText": "other", "lemma": "other", "characterOffsetBegin": 9, "characterOffsetEnd": 14, "pos": "JJ", "before": " ", "after": " "}, {"index": 5, "word": "five", "originalText": "five", "lemma": "five", "characterOffsetBegin": 15, "characterOffsetEnd": 19, "pos": "CD", "before": " ", "after": " "}, {"index": 6, "word": "I", "originalText": "I", "lemma": "I", "characterOffsetBegin": 20, "characterOffsetEnd": 21, "pos": "PRP", "before": " ", "after": ""}, {"index": 7, "word": "'m", "originalText": "'m", "lemma": "be", "characterOffsetBegin": 21, "characterOffsetEnd": 23, "pos": "VBP", "before": "", "after": " "}, {"index": 8, "word": "worried", "originalText": "worried", "lemma": "worried", "characterOffsetBegin": 24, "characterOffsetEnd": 31, "pos": "JJ", "before": " ", "after": " "}, {"index": 9, "word": "about", "originalText": "about", "lemma": "about", "characterOffsetBegin": 32, "characterOffsetEnd": 37, "pos": "IN", "before": " ", "after": ""}, {"index": 10, "word": ".", "originalText": ".", "lemma": ".", "characterOffsetBegin": 37, "characterOffsetEnd": 38, "pos": ".", "before": "", "after": ""}], "ext_links": {"frame": ["be", "Performers_and_roles"], "synsets": [{"lemma": "be", "synset": "Synset('be.v.01')", "definition": "have the quality of being; (copula, used with an adjective or a predicate noun)", "lemma_names": ["be"], "_examples": ["John is rich", "This is not a good answer"]}, {"lemma": "be", "synset": "Synset('be.v.02')", "definition": "be identical to; be someone or something", "lemma_names": ["be"], "_examples": ["The president of the company is John Smith", "This is my house"]}, {"lemma": "be", "synset": "Synset('be.v.03')", "definition": "occupy a certain position or area; be somewhere", "lemma_names": ["be"], "_examples": ["Where is my umbrella?\" \"The toolshed is in the back", "What is behind this behavior?"]}, {"lemma": "be", "synset": "Synset('exist.v.01')", "definition": "have an existence, be extant", "lemma_names": ["exist", "be"], "_examples": ["Is there a God?"]}, {"lemma": "be", "synset": "Synset('be.v.05')", "definition": "happen, occur, take place; this was during the visit to my parents' house\"", "lemma_names": ["be"], "_examples": ["I lost my wallet", "There were two hundred people at his funeral", "There was a lot of noise in the kitchen"]}, {"lemma": "be", "synset": "Synset('equal.v.01')", "definition": "be identical or equivalent to", "lemma_names": ["equal", "be"], "_examples": ["One dollar equals 1,000 rubles these days!"]}, {"lemma": "be", "synset": "Synset('constitute.v.01')", "definition": "form or compose", "lemma_names": ["constitute", "represent", "make_up", "comprise", "be"], "_examples": ["This money is my only income", "The stone wall was the backdrop for the performance", "These constitute my entire belonging", "The children made up the chorus", "This sum represents my entire income for a year", "These few men comprise his entire army"]}, {"lemma": "be", "synset": "Synset('be.v.08')", "definition": "work in a specific place, with a specific subject, or in a specific function", "lemma_names": ["be", "follow"], "_examples": ["He is a herpetologist", "She is our resident philosopher"]}, {"lemma": "be", "synset": "Synset('embody.v.02')", "definition": "represent, as of a character on stage", "lemma_names": ["embody", "be", "personify"], "_examples": ["Derek Jacobi was Hamlet"]}, {"lemma": "be", "synset": "Synset('be.v.10')", "definition": "spend or use time", "lemma_names": ["be"], "_examples": ["I may be an hour"]}, {"lemma": "be", "synset": "Synset('be.v.11')", "definition": "have life, be alive", "lemma_names": ["be", "live"], "_examples": ["Our great leader is no more", "My grandfather lived until the end of war"]}, {"lemma": "be", "synset": "Synset('be.v.12')", "definition": "to remain unmolested, undisturbed, or uninterrupted -- used only in infinitive form", "lemma_names": ["be"], "_examples": ["let her be"]}, {"lemma": "be", "synset": "Synset('cost.v.01')", "definition": "be priced at", "lemma_names": ["cost", "be"], "_examples": ["These shoes cost $100"]}]}, "characters": ["", "", "", "", "", "Monica", "", "", "", ""], "sid": "6-1", "origin_sent": "It's the other five I'm worried about.", "triple": {"sbj": "Monica", "rel": "be", "obj": "worried"}, "intention": ["It", "'s", "the", "other", "five", "about"]}]}